<?xml version="1.0" encoding="utf-8" ?><dwsync><file name="audio.php" server="clubfustudio.com" local="3412125900" remote="20591995084" /><file name="browser.php" server="clubfustudio.com" local="3412125900" remote="20591995084" /><file name="index.php" server="clubfustudio.com" local="3412125900" remote="20591995084" /><file name="item.php" server="clubfustudio.com" local="3412125900" remote="20591995084" /><file name="polaroid.php" server="clubfustudio.com" local="3412125900" remote="20591995084" /><file name="updateorder.php" server="clubfustudio.com" local="3412125900" remote="20591995084" /><file name="audio.php" server="s13939.gridserver.com/domains/peterlowells.com/html/" local="3412125900" remote="12005926352" /><file name="browser.php" server="s13939.gridserver.com/domains/peterlowells.com/html/" local="3412125900" remote="12005926352" /><file name="index.php" server="s13939.gridserver.com/domains/peterlowells.com/html/" local="3412125900" remote="12005926352" /><file name="item.php" server="s13939.gridserver.com/domains/peterlowells.com/html/" local="3412125900" remote="12005926352" /><file name="polaroid.php" server="s13939.gridserver.com/domains/peterlowells.com/html/" local="3412125900" remote="12005926352" /><file name="updateorder.php" server="s13939.gridserver.com/domains/peterlowells.com/html/" local="3412125900" remote="12005926352" /></dwsync>